README.md
setup.cfg
setup.py
airtools/__init__.py
airtools/kaczmarz.py
airtools/logmart.py
airtools/lsqlin.py
airtools/maxent.py
airtools/picard.py
airtools/rzr.py
airtools.egg-info/PKG-INFO
airtools.egg-info/SOURCES.txt
airtools.egg-info/dependency_links.txt
airtools.egg-info/requires.txt
airtools.egg-info/top_level.txt