Metadata-Version: 2.1
Name: airtools
Version: 1.2.0
Summary: Python port of Matlab AIRtools and ReguTools regularization toolbox
Home-page: https://github.com/scivision/airtools
Author: Michael Hirsch, Ph.D.
Author-email: scivision@users.noreply.github.com
License: UNKNOWN
Keywords: regularization
Platform: UNKNOWN
Classifier: Development Status :: 5 - Production/Stable
Classifier: Environment :: Console
Classifier: Intended Audience :: End Users/Desktop
Classifier: Operating System :: OS Independent
Classifier: Programming Language :: Python :: 3.5
Classifier: Programming Language :: Python :: 3.6
Classifier: Programming Language :: Python :: 3.7
Classifier: Programming Language :: Python :: 3.8
Classifier: Programming Language :: Python :: Implementation :: CPython
Classifier: Topic :: Scientific/Engineering
Classifier: Topic :: Utilities
Requires-Python: >= 3.5
Provides-Extra: tests
Provides-Extra: lint
